{
  "url": "https://avalon.law.yale.edu/imt/judsent.asp",
  "doc_type": "vol1_doc",
  "title": "Judgement : Sentences",
  "full_text": "Judgement : Sentences\nPrevious Document\nJudgment Contents\nNext Document\nTHE PRESIDENT: Before pronouncing sentence on any of the defendants, and while all of the defendants are present, the Tribunal takes the occasion to advise them that any applications for clemency of the Control Council must be lodged with the General Secretary of this Tribunal within four days from today.\nThe Tribunal will now adjourn and will sit again at ten minutes to three.\n(A recess was taken until 2.50 p.m.)\n2.50 p.m.\nThe PRESIDENT: In accordance with\nArticle 27 of the Charter\n, the International Military Tribunal will now pronounce the sentences on the defendants convicted on this\nIndictment\n.\nDefendant Hermann Wilhelm Goering\n, on the counts of the\nIndictment\non which you have been convicted, the International Military Tribunal sentences you to death by hanging.\nDefendant Rudolf Hess\n, on the counts of the\nIndictment\non which you have been convicted, the Tribunal sentences you to imprisonment for life.\nDefendant Joachim von Ribbentrop\n, on the counts of the\nIndictment\non which you have been convicted, the Tribunal sentences you to death by hanging.\nDefendant Wilhelm Keitel\n, on the counts of the\nIndictment\non which you have been convicted, the Tribunal sentences you to death by hanging.\nDefendant Ernst Kaltenbrunner\n, on the counts of the\nIndictment\non which you have been convicted. the Tribunal sentences you to death by hanging.\nDefendant Alfred Rosenberg\n, on the counts of the\nIndictment\non which you have been convicted, the Tribunal sentences you to death by hanging.\nDefendant Hans Frank\n, on the counts of the\nIndictment\non which you have been convicted, the Tribunal sentences you to death by hanging.\nDefendant Wilhelm Frick, on the counts of the\nIndictment\non which you have been convicted, the Tribunal sentences you to death by hanging.\nDefendant Julius Streicher\n, on the count of the\nIndictment\non which you have been convicted, The Tribunal sentences you to death by hanging.\nDefendant Walther Funk\n, on the counts of the\nIndictment\non which you have been convicted, the Tribunal sentences You to imprisonment for life\nDefendant Karl Doenitz\n, on the counts of the\nIndictment\non which you have been convicted, the Tribunal sentences you to ten years imprisonment.\nDefendant Erich Raeder\n, on the counts of the\nIndictment\non which you have been convicted, the Tribunal sentences you to imprisonment for life.\nDefendant Baldur von Schirach\n, on the counts of the\nIndictment\non which you have been convicted, the Tribunal sentences you to twenty years imprisonment.\nDefendant Fritz Sauckel, on the counts of the\nIndictment\non which you have been convicted, the Tribunal sentences you to death by hanging.\nDefendant Alfred Jodl\n, on the counts of the\nIndictment\non which you have been convicted, the Tribunal sentences you to death by hanging.\nDefendant Arthur Seyss-Inquart\n, on the counts of the\nIndictment\non which you have been convicted, the Tribunal sentences you to death by hanging.\nDefendant Albert Speer\n, on the counts of the\nIndictment\non which you have been convicted, the Tribunal sentences you to twenty years imprisonment.\nDefendant Konstantin von Neurath\n, on the counts of the\nIndictment\non which you have been convicted, the Tribunal sentences you to fifteen years imprisonment.\nThe Tribunal sentences the Defendant Martin Bormann\n. on the counts of the\nIndictment\non which he has been convicted, to death by hanging.\nI have an announcement to make. The Soviet Member of the International Military Tribunal desires to record his dissent from the decisions in the cases of the Defendants Schacht, von Papen, and Fritzsche. He is of the opinion that they should have been convicted and not acquitted.\nHe also dissents from the decisions in respect of the Reichs Cabinet, the General Staff and High Command, being of the opinion that they should have been declared to be criminal organisations.\nHe also dissents from the decision in the case of the sentence on the Defendant Hess, and is of the opinion that the sentence should have been death, and not life imprisonment.\nThis\ndissenting opinion\nwill be put into writing and annexed to the judgment and will be published as soon as possible.\n(The Tribunal adjourned.)\nPrevious Document\nJudgment Contents\nNext Document",
  "page_numbers": [],
  "page_format": "NONE",
  "char_count": 11455,
  "word_count": 711,
  "scrape_timestamp": "2026-03-07T17:22:14.463828+00:00",
  "validation_flags": [],
  "content_hash": "cdc0971f0c54d92dca372357afee2b51"
}