{
  "url": "https://avalon.law.yale.edu/imt/1725-ps.asp",
  "doc_type": "nca_v4",
  "title": "Nazi Conspiracy and Aggression Volume IVDocument No. 1725-PS",
  "full_text": "Nazi Conspiracy and Aggression Volume IV\nDocument No. 1725-PS\nPrevious Document\nVolume IV Menu\nNext Document\nTRANSLATION OF DOCUMENT 1725-PS\n1935 REICHSGESETZBLATT, PART I, PAGE 502\nOrdinance on Enforcement of the Law for Securing the Unity of Party and State of 29 March 1935\nBy virtue of the law for securing the unity of Party and State of 1 December 1933 (RGBl I, 1016) I order:\nARTICLE 1\n1. The NSDAP and the Hitler Youth Movement, Inc. are to be expunged in the corporation register. The property of these corporations has without liquidation become the property of the NSDAP as a corporation of public law.\n2. The land deeds and other public records are to be corrected free of charge on request.\n3. Until the decree of the statute of the NSDAP (Article 1, Section 2 of the Law for Securing the Unity of Party and State of 1 December 1933), the previous statute of the National Socialist German Workers' Corporation, Inc., is applicable in this sense to the NSDAP as a corporation of public law.\nARTICLE 2\nThe SA,\nThe SS,\nThe National Socialist Driver Corps [Kraftfahrkorps].\nThe Hitler Youth (including the Jungfolk, the League of German Girls and Jungmaedel).\nThe National Socialist German Student League,\nThe National Socialist German Women's Auxiliary [Frauenschaft], are components of the party.\nARTICLE 3\nThe National Socialist League of German Physicians, Inc.,\nThe League of National Socialist German Jurists, Inc.\nThe National Socialist Teachers' League, Inc.,\nThe National Socialist People's Welfare, Inc.,\nThe National Socialist War Veterans' Administration, Inc.,\nThe Reich League of German Officials, Inc.,\nThe National Socialist League of German Technologists,\nThe German Labor Front (including the National Socialist foundation \"Kraft durch Freude\")\nare the organizations affiliated to the NSDAP.\nARTICLE 4\n1. The components of the NSDAP possess no legal character of their own and no property of their own.\n2. The NSDAP forms with its components as a corporation of public law, a unit for the domain of the entire organization, with reference to property rights. Therefore the entire corporation is exclusively obligated and justified as to property rights.\n3. The Reich Treasurer of the NSDAP is the Plenipotentiary of the Fuehrer in all legal matters relating to property of the NSDAP. The Plenipotentiary rights include the right to assign sub-powers of attorney generally or for individual matters.\nARTICLE 5\n1. The affiliated organizations can possess their own legal character.\n2. The affiliated organizations are subject to the financial supervision of the Reich Treasurer of the NSDAP.\n3. The other legally determined supervisory rights are not touched by the financial supervision of the Reich Treasurer of the NSDAP.\nARTICLE 6\nAll authorities have to assist the Reich Treasurer of the NSDAP and his agent in the fulfillment of his duties and to conform with the requests of the Reich Treasurer of the NSDAP, which go to them on the basis of this order.\nARTICLE 7\n1. The first enforcement order of 23 March 1934 (Voelkischer Beobachter, Munich edition No. 86 of 27 March 1934 and Berlin edition No. 87 of 28 March 1934) on the law for securing unity of party and state dated 1 December 1933 is abrogated.\n2. Likewise all previous orders and regulations contrary to the above enforcement order on the law for securing unity of party and state of 1 December 1933 are abrogated.\nARTICLE 8\n1. The Deputy of the Fuehrer issues terms for enforcement and supplementing Articles 2 and 3 of this order. The Reich Treasurer of the NSDAP issues the remaining terms for execution of this order.\n2. This law takes effect on the day following its announcement.\nBerlin, 29 March 1935\nThe Fuehrer and Reich Chancellor\nAdolf Hitler\nThe Deputy of the Fuehrer\nR. Hess\nReich Minister without Portfolio\nThe Reich Minister of the Interior\nFrick\nSource:\nNazi Conspiracy and Aggression Volume IV\nOffice of the United States Chief Counsel for Prosecution of Axis Criminality\nWashington, DC : United States Government Printing Office, 1946\nPrevious Document\nVolume IV Menu\nNext Document",
  "page_numbers": [],
  "page_format": "NONE",
  "char_count": 11279,
  "word_count": 670,
  "scrape_timestamp": "2026-03-07T17:38:45.753169+00:00",
  "validation_flags": [
    "POSSIBLE_TRUNCATION"
  ],
  "content_hash": "4432161b55375f05974ccb09ce7d7d55"
}